dtx_to_wif/__init__.py
dtx_to_wif/dtx_reader.py
dtx_to_wif/pattern_data.py
dtx_to_wif/pattern_reader.py
dtx_to_wif/py.typed
dtx_to_wif/run_x_to_wif.py
dtx_to_wif/version.py
dtx_to_wif/wif_reader.py
dtx_to_wif/wif_writer.py
dtx_to_wif/wpo_reader.py
test_data/bad_dtx/missing color_table warp.dtx
test_data/bad_dtx/missing color_table weft.dtx
test_data/bad_dtx/missing liftplan.dtx
test_data/bad_dtx/missing tieup.dtx
test_data/bad_dtx/missing treadling.dtx
test_data/bad_dtx/too many treadles in treadling.dtx
test_data/bad_dtx/warp_color too big.dtx
test_data/bad_dtx/warp_color too small.dtx
test_data/bad_dtx/weft_color too big.dtx
test_data/bad_dtx/weft_color too small.dtx
test_data/bad_wif/default warp color too big.wif
test_data/bad_wif/default warp color too small.wif
test_data/bad_wif/default weft color too big.wif
test_data/bad_wif/default weft color too small.wif
test_data/bad_wif/missing liftplan.wif
test_data/bad_wif/missing tieup.wif
test_data/bad_wif/missing treadling.wif
test_data/bad_wif/missing_color_table_warp.wif
test_data/bad_wif/missing_color_table_weft.wif
test_data/bad_wif/too many treadles in treadline.wif
test_data/bad_wif/warp_color too big.wif
test_data/bad_wif/warp_color too small.wif
test_data/bad_wif/weft_color too big.wif
test_data/bad_wif/weft_color too small.wif
test_data/basic_dtx/many color liftplan and zeros.dtx
test_data/basic_dtx/many color multiple treadles and zeros.dtx
test_data/basic_dtx/many color single treadles.dtx
test_data/basic_dtx/level2/two color liftplan.dtx
test_data/basic_dtx/level2/two color multiple treadles.dtx
test_data/basic_dtx/level2/two color single treadles.dtx
test_data/basic_wif/liftplan with defaults.wif
test_data/basic_wif/treadles with defaults.wif
test_data/basic_wpo/many color liftplan and zeros.wpo
test_data/basic_wpo/many color liftplan and zeros.wpo.wif
test_data/basic_wpo/many color multiple treadles and zeros.wpo
test_data/basic_wpo/many color multiple treadles and zeros.wpo.wif
dtx_to_wif-4.4.dist-info/METADATA
dtx_to_wif-4.4.dist-info/WHEEL
dtx_to_wif-4.4.dist-info/entry_points.txt
dtx_to_wif-4.4.dist-info/top_level.txt
dtx_to_wif-4.4.dist-info/RECORD
