Metadata-Version: 2.4
Name: dtx_to_wif
Version: 4.4
Summary: Convert handweaving files from dtx format (FiberWorks) to wif
Author-email: Russell Owen <r3owen@gmail.com>
Project-URL: Homepage, https://pypi.org/project/dtx-to-wif/
Project-URL: Documentation, https://r-owen.github.io/dtx_to_wif/
Project-URL: Source, https://github.com/r-owen/dtx_to_wif
Project-URL: Issues, https://github.com/r-owen/dtx_to_wif/issues
Classifier: Programming Language :: Python :: 3
Classifier: License :: OSI Approved :: MIT License
Classifier: Operating System :: OS Independent
Requires-Python: >=3.10
Provides-Extra: dev
Requires-Dist: pre-commit; extra == "dev"
Requires-Dist: mkdocs; extra == "dev"
Requires-Dist: mkapi; extra == "dev"
Requires-Dist: sphinx; extra == "dev"
Requires-Dist: sphinxcontrib-napoleon; extra == "dev"
